sog4onnx/__init__.py
sog4onnx/__main__.py
sog4onnx/onnx_operation_generator.py
sog4onnx-1.0.16.dist-info/LICENSE
sog4onnx-1.0.16.dist-info/METADATA
sog4onnx-1.0.16.dist-info/WHEEL
sog4onnx-1.0.16.dist-info/entry_points.txt
sog4onnx-1.0.16.dist-info/top_level.txt
sog4onnx-1.0.16.dist-info/RECORD
