Metadata-Version: 2.1
Name: sog4onnx
Version: 1.0.16
Summary: Simple ONNX operation generator. Simple Operation Generator for ONNX.
Home-page: https://github.com/PINTO0309/sog4onnx
Author: Katsuya Hyodo
Author-email: rmsdh122@yahoo.co.jp
License: MIT License
Platform: linux
Platform: unix
Requires-Python: >=3.6
License-File: LICENSE
